vitabs/__init__.py
vitabs/commands.py
vitabs/editor.py
vitabs/music.py
vitabs/player.py
vitabs/symbols.py
vitabs/tablature.py
vitabs-1.0.data/scripts/vitabs
vitabs-1.0.dist-info/COPYING
vitabs-1.0.dist-info/METADATA
vitabs-1.0.dist-info/WHEEL
vitabs-1.0.dist-info/top_level.txt
vitabs-1.0.dist-info/RECORD
