Metadata-Version: 2.1
Name: vitabs
Version: 1.0
Summary: Vi-inspired guitar tab editor
Home-page: http://github.com/pstiasny/VITABS
Author: Pawel Stiasny
Author-email: pawelstiasny@gmail.com
License: GNU General Public License
Project-URL: Manual, https://github.com/pstiasny/VITABS/blob/master/doc/index.md
Platform: UNKNOWN
Provides-Extra: midi
Requires-Dist: python-rtmidi ; extra == 'midi'
